sych_llm_playground/__init__.py
sych_llm_playground/__main__.py
sych_llm_playground/cleanup.py
sych_llm_playground/configure.py
sych_llm_playground/deploy.py
sych_llm_playground/interact.py
sych_llm_playground/list.py
sych_llm_playground/providers/aws/__init__.py
sych_llm_playground/providers/aws/cleanup.py
sych_llm_playground/providers/aws/configure.py
sych_llm_playground/providers/aws/deploy.py
sych_llm_playground/providers/aws/interact.py
sych_llm_playground/providers/aws/list.py
sych_llm_playground/providers/aws/utils/__init__.py
sych_llm_playground/providers/aws/utils/credentials.py
sych_llm_playground/providers/aws/utils/resources.py
sych_llm_playground/py.typed
sych_llm_playground/utils/__init__.py
sych_llm_playground/utils/loader.py
sych_llm_playground/utils/provider_selection.py
sych_llm_playground-0.3.0.dist-info/entry_points.txt
sych_llm_playground-0.3.0.dist-info/LICENSE
sych_llm_playground-0.3.0.dist-info/WHEEL
sych_llm_playground-0.3.0.dist-info/METADATA
sych_llm_playground-0.3.0.dist-info/RECORD
