Metadata-Version: 2.1
Name: sych-llm-playground
Version: 0.3.0
Summary: Sych LLM Playground is a command line tool deploy and interact with language models on the cloud.
Home-page: https://github.com/sychhq/sych-llm-playground
License: Apache-2.0
Author: Sych Inc.
Author-email: dev@sych.io
Requires-Python: >=3.10,<4.0
Classifier: Development Status :: 3 - Alpha
Classifier: License :: OSI Approved :: Apache Software License
Classifier: Programming Language :: Python :: 3
Classifier: Programming Language :: Python :: 3.10
Requires-Dist: boto3 (>=1.28.29,<2.0.0)
Requires-Dist: click (>=8.0.1)
Requires-Dist: inquirer (>=3.1.3,<4.0.0)
Requires-Dist: sagemaker (==2.177.1)
Project-URL: Changelog, https://github.com/sychhq/sych-llm-playground/releases
Project-URL: Documentation, https://sych-llm-playground.readthedocs.io
Project-URL: Repository, https://github.com/sychhq/sych-llm-playground
